[
  {
    "id": "pass_001",
    "userId": "user_sarah",
    "userEmail": "sarah.chen@email.com",
    "userName": "Sarah Chen",
    "businessId": "g1",
    "businessName": "FitZone Premium Gym",
    "passType": "weekly",
    "shift": "morning",
    "sessionDuration": 120,
    "price": 1499,
    "status": "active",
    "purchasedAt": "2026-02-01T10:00:00Z",
    "activatedAt": "2026-02-02T08:00:00Z",
    "expiresAt": "2026-02-09T23:59:59Z",
    "usedDays": 4,
    "totalDays": 7,
    "daysExtended": 0,
    "transactionId": "txn_001"
  },
  {
    "id": "pass_002",
    "userId": "user_mike",
    "userEmail": "mike.johnson@email.com",
    "userName": "Mike Johnson",
    "businessId": "g2",
    "businessName": "Iron Paradise Gym",
    "passType": "monthly",
    "shift": "evening",
    "sessionDuration": 180,
    "price": 5499,
    "status": "active",
    "purchasedAt": "2026-01-15T14:00:00Z",
    "activatedAt": "2026-01-16T15:00:00Z",
    "expiresAt": "2026-02-15T23:59:59Z",
    "usedDays": 18,
    "totalDays": 30,
    "daysExtended": 1,
    "transactionId": "txn_002"
  },
  {
    "id": "pass_003",
    "userId": "user_priya",
    "userEmail": "priya.sharma@email.com",
    "userName": "Priya Sharma",
    "businessId": "l1",
    "businessName": "Central Library Hub",
    "passType": "monthly",
    "shift": "fullday",
    "sessionDuration": 240,
    "price": 1499,
    "status": "active",
    "purchasedAt": "2026-02-01T09:00:00Z",
    "activatedAt": "2026-02-01T10:00:00Z",
    "expiresAt": "2026-03-03T23:59:59Z",
    "usedDays": 6,
    "totalDays": 30,
    "daysExtended": 0,
    "transactionId": "txn_003"
  },
  {
    "id": "pass_004",
    "userId": "user_alex",
    "userEmail": "alex.kumar@email.com",
    "userName": "Alex Kumar",
    "businessId": "g1",
    "businessName": "FitZone Premium Gym",
    "passType": "weekly",
    "shift": "morning",
    "sessionDuration": 60,
    "price": 1499,
    "status": "inactive",
    "purchasedAt": "2026-02-05T16:00:00Z",
    "usedDays": 0,
    "totalDays": 7,
    "daysExtended": 0,
    "transactionId": "txn_004"
  },
  {
    "id": "pass_005",
    "userId": "user_emma",
    "userEmail": "emma.wilson@email.com",
    "userName": "Emma Wilson",
    "businessId": "g3",
    "businessName": "Zen Yoga Studio",
    "passType": "weekly",
    "shift": "morning",
    "sessionDuration": 120,
    "price": 1899,
    "status": "expired",
    "purchasedAt": "2026-01-20T11:00:00Z",
    "activatedAt": "2026-01-21T07:00:00Z",
    "expiresAt": "2026-01-28T23:59:59Z",
    "usedDays": 7,
    "totalDays": 7,
    "daysExtended": 0,
    "transactionId": "txn_005"
  }
]
